pystoch/__init__.py
pystoch/detectors.py
pystoch/gmst.py
pystoch/orf.py
pystoch/pystoch_parameter.py
pystoch/pystochmap.py
pystoch/tdelay_response.py
pystoch-1.0.2.dist-info/LICENSE
pystoch-1.0.2.dist-info/METADATA
pystoch-1.0.2.dist-info/WHEEL
pystoch-1.0.2.dist-info/top_level.txt
pystoch-1.0.2.dist-info/RECORD
