Metadata-Version: 2.1
Name: pystoch
Version: 1.0.2
Summary: A Python package for Stochastic Gravitational Wave background
Home-page: https://github.com/Sudhagar7/PyStoch
Author: Anirban Ani, Jishnu Suresh, Sudhagar Suyamprakasam
Author-email: sudhagar.suyamprakasam@ligo.org
License: MIT License
Platform: UNKNOWN
Classifier: Development Status :: 4 - Beta
Classifier: Intended Audience :: Science/Research
Classifier: License :: OSI Approved :: GNU General Public License v3 (GPLv3)
Classifier: Operating System :: Unix
Classifier: Operating System :: MacOS
Classifier: Operating System :: POSIX
Classifier: Programming Language :: Python
Classifier: Programming Language :: Python :: 3
Classifier: Programming Language :: Python :: 3.6
Classifier: Programming Language :: Python :: 3.7
Classifier: Topic :: Scientific/Engineering :: Astronomy
Classifier: Topic :: Scientific/Engineering :: Physics
Provides: pystoch
Requires-Python: >=3.0
Requires-Dist: configparser (>=3.5.0)
Requires-Dist: matplotlib (>=1.5.1)
Requires-Dist: numpy (>=1.14.2)
Requires-Dist: h5py (>=2.7.1)
Requires-Dist: healpy (>=1.11.0)
Requires-Dist: six (>=1.12.0)
